pygame_plot/__init__.py
pygame_plot-0.1.dist-info/LICENSE
pygame_plot-0.1.dist-info/METADATA
pygame_plot-0.1.dist-info/WHEEL
pygame_plot-0.1.dist-info/top_level.txt
pygame_plot-0.1.dist-info/RECORD
