Metadata-Version: 2.1
Name: pygame-plot
Version: 0.1
Summary: Quick visualization of data using pygame with a matplotlib style
Home-page: https://github.com/LSaffin/pygame_plot
Author: Leo Saffin
Author-email: string_buster@hotmail.com
License: MIT
Platform: UNKNOWN
Classifier: Development Status :: 2 - Pre-Alpha
Classifier: License :: OSI Approved :: MIT License
Classifier: Programming Language :: Python
Classifier: Programming Language :: Python :: 2
Classifier: Programming Language :: Python :: 3
Classifier: Topic :: Scientific/Engineering :: Visualization
Requires-Dist: pygame
Requires-Dist: matplotlib
Requires-Dist: numpy
